converterapi/__init__.py
converterapi/converterapi.py
converterapi/data.py
converterapi-1.0.0.dist-info/METADATA
converterapi-1.0.0.dist-info/WHEEL
converterapi-1.0.0.dist-info/top_level.txt
converterapi-1.0.0.dist-info/RECORD
