Metadata-Version: 2.1
Name: converterapi
Version: 1.0.0
Summary: Test Converter
Home-page: UNKNOWN
Author: jiminlee
Author-email: jimin.lee@nota.ai
License: UNKNOWN
Platform: UNKNOWN
Requires-Python: >=3
Requires-Dist: mock
Requires-Dist: polling2
Requires-Dist: requests
Requires-Dist: urllib3
